task3/ram2ports.sv
module ram2ports #(
    parameter ADDRESS_WIDTH = 8,
              DATA_WIDTH    = 8
)(
    input  logic                     clk,
    input  logic                     wr_en,
    input  logic                     rd_en,
    input  logic [ADDRESS_WIDTH-1:0] wr_addr,
    input  logic [ADDRESS_WIDTH-1:0] rd_addr,
    input  logic [DATA_WIDTH-1:0]    din,
    output logic [DATA_WIDTH-1:0]    dout
);

logic [DATA_WIDTH-1:0] ram_array [2**ADDRESS_WIDTH-1:0];

always_ff @(posedge clk) begin
    if (wr_en == 1'b1)
        ram_array[wr_addr] <= din;

    if (rd_en == 1'b1)
        // output is synchronous
        dout <= ram_array[rd_addr];
end

endmodule

task1/counter.sv
module counter #(
    parameter WIDTH = 8
)(

    input  logic             clk,
    input  logic             rst,
    input  logic             en,
    input  logic [WIDTH-1:0] step,
    output logic [WIDTH-1:0] count
);

always_ff @ (posedge clk or posedge rst) // asynchronous reset
    if (rst) count <= {WIDTH{1'b0}};
    else     count <= count + step;

endmodule

task3/sigdelay.sv
module sigdelay #(
    parameter ADDRESS_WIDTH = 9,
              DATA_WIDTH    = 8
)(
    input  logic                     clk,
    input  logic                     rst,
    input  logic                     wr,
    input  logic                     rd,
    input  logic [DATA_WIDTH-1:0]    mic_signal,     // input audio sample
    input  logic [ADDRESS_WIDTH-1:0] offset,         // delay offset
    output logic [DATA_WIDTH-1:0]    delayed_signal  // delayed output
);

    // Internal wires
    logic [ADDRESS_WIDTH-1:0] address;
    logic [DATA_WIDTH-1:0]    ram_out;

    // Address counter — cycles through RAM locations
    counter #(ADDRESS_WIDTH) addrCounter (
        .clk   (clk),
        .rst   (rst),
        .en    (1'b1),
        .count (address)
    );

    // Dual-port RAM for delay effect
    ram2ports #(
        .ADDRESS_WIDTH(ADDRESS_WIDTH),
        .DATA_WIDTH(DATA_WIDTH)
    ) delayRAM (
        .clk     (clk),
        .wr_en   (wr),
        .rd_en   (rd),
        .wr_addr (address),
        .rd_addr (address - offset),  // delayed read address
        .din     (mic_signal),
        .dout    (ram_out)
    );

    // Connect delayed output
    assign delayed_signal = ram_out;

endmodule

task3/sigdelay.vcd
$version Generated by VerilatedVcd $end
$date Wed Oct 29 14:51:12 2025 $end
$timescale 1ps $end

 $scope module TOP $end
  $var wire  1 # clk $end
  $var wire  8 ) delayed_signal [7:0] $end
  $var wire  8 ' mic_signal [7:0] $end
  $var wire  9 ( offset [8:0] $end
  $var wire  1 & rd $end
  $var wire  1 $ rst $end
  $var wire  1 % wr $end
  $scope module sigdelay $end
   $var wire 32 - ADDRESS_WIDTH [31:0] $end
   $var wire 32 . DATA_WIDTH [31:0] $end
   $var wire  9 * address [8:0] $end
   $var wire  1 # clk $end
   $var wire  8 ) delayed_signal [7:0] $end
   $var wire  8 ' mic_signal [7:0] $end
   $var wire  9 ( offset [8:0] $end
   $var wire  8 + ram_out [7:0] $end
   $var wire  1 & rd $end
   $var wire  1 $ rst $end
   $var wire  1 % wr $end
   $scope module addrCounter $end
    $var wire 32 - WIDTH [31:0] $end
    $var wire  1 # clk $end
    $var wire  9 * count [8:0] $end
    $var wire  1 / en $end
    $var wire  1 $ rst $end
    $var wire  9 0 step [8:0] $end
   $upscope $end
   $scope module delayRAM $end
    $var wire 32 - ADDRESS_WIDTH [31:0] $end
    $var wire 32 . DATA_WIDTH [31:0] $end
    $var wire  1 # clk $end
    $var wire  8 ' din [7:0] $end
    $var wire  8 + dout [7:0] $end
    $var wire  9 , rd_addr [8:0] $end
    $var wire  1 & rd_en $end
    $var wire  9 * wr_addr [8:0] $end
    $var wire  1 % wr_en $end
   $upscope $end
  $upscope $end
 $upscope $end
$enddefinitions $end


#0
1#
0$
1%
1&
b00000000 '
b001000000 (
b00000000 )
b000000000 *
b00000000 +
b111000000 ,
b00000000000000000000000000001001 -
b00000000000000000000000000001000 .
1/
b000000000 0
#1
0#
#2
1#
b01101100 '
b000101000 (
b000000001 *
b111011001 ,
#3
0#
#4
1#
b01101011 '
b000000010 *
b111011010 ,
#5
0#
#6
1#
b01100111 '
b000000011 *
b111011011 ,
#7
0#
#8
1#
b01101011 '
b000000100 *
b111011100 ,
#9
0#
#10
1#
b01101001 '
b000000101 *
b111011101 ,
#11
0#
#12
1#
b01101000 '
b000000110 *
b111011110 ,
#13
0#
#14
1#
b01101001 '
b000000111 *
b111011111 ,
#15
0#
#16
1#
b01101010 '
b000001000 *
b111100000 ,
#17
0#
#18
1#
b01101011 '
b000001001 *
b111100001 ,
#19
0#
#20
1#
b01101100 '
b000001010 *
b111100010 ,
#21
0#
#22
1#
b000001011 *
b111100011 ,
#23
0#
#24
1#
b01101101 '
b000001100 *
b111100100 ,
#25
0#
#26
1#
b01101100 '
b000001101 *
b111100101 ,
#27
0#
#28
1#
b000001110 *
b111100110 ,
#29
0#
#30
1#
b01101111 '
b000001111 *
b111100111 ,
#31
0#
#32
1#
b01110010 '
b000010000 *
b111101000 ,
#33
0#
#34
1#
b01101111 '
b000010001 *
b111101001 ,
#35
0#
#36
1#
b01110011 '
b000010010 *
b111101010 ,
#37
0#
#38
1#
b01110010 '
b000010011 *
b111101011 ,
#39
0#
#40
1#
b01110001 '
b000010100 *
b111101100 ,
#41
0#
#42
1#
b01110000 '
b000010101 *
b111101101 ,
#43
0#
#44
1#
b000010110 *
b111101110 ,
#45
0#
#46
1#
b01110011 '
b000010111 *
b111101111 ,
#47
0#
#48
1#
b01110001 '
b000011000 *
b111110000 ,
#49
0#
#50
1#
b01110011 '
b000011001 *
b111110001 ,
#51
0#
#52
1#
b01110010 '
b000011010 *
b111110010 ,
#53
0#
#54
1#
b01101111 '
b000011011 *
b111110011 ,
#55
0#
#56
1#
b01101100 '
b000011100 *
b111110100 ,
#57
0#
#58
1#
b000011101 *
b111110101 ,
#59
0#
#60
1#
b01101111 '
b000011110 *
b111110110 ,
#61
0#
#62
1#
b000011111 *
b111110111 ,
#63
0#
#64
1#
b000100000 *
b111111000 ,
#65
0#
#66
1#
b01101010 '
b000100001 *
b111111001 ,
#67
0#
#68
1#
b01101011 '
b000100010 *
b111111010 ,
#69
0#
#70
1#
b01101010 '
b000100011 *
b111111011 ,
#71
0#
#72
1#
b000100100 *
b111111100 ,
#73
0#
#74
1#
b01101100 '
b000100101 *
b111111101 ,
#75
0#
#76
1#
b01101110 '
b000100110 *
b111111110 ,
#77
0#
#78
1#
b01110010 '
b000100111 *
b111111111 ,
#79
0#
#80
1#
b01101111 '
b000101000 *
b000000000 ,
#81
0#
#82
1#
b01110010 '
b000101001 *
b000000001 ,
#83
0#
#84
1#
b01110011 '
b01101100 )
b000101010 *
b01101100 +
b000000010 ,
#85
0#
#86
1#
b01110100 '
b01101011 )
b000101011 *
b01101011 +
b000000011 ,
#87
0#
#88
1#
b01110000 '
b01100111 )
b000101100 *
b01100111 +
b000000100 ,
#89
0#
#90
1#
b01101111 '
b01101011 )
b000101101 *
b01101011 +
b000000101 ,
#91
0#
#92
1#
b01101100 '
b01101001 )
b000101110 *
b01101001 +
b000000110 ,
#93
0#
#94
1#
b01101000 )
b000101111 *
b01101000 +
b000000111 ,
#95
0#
#96
1#
b01101001 )
b000110000 *
b01101001 +
b000001000 ,
#97
0#
#98
1#
b01101010 '
b01101010 )
b000110001 *
b01101010 +
b000001001 ,
#99
0#
#100
1#
b01101110 '
b01101011 )
b000110010 *
b01101011 +
b000001010 ,
#101
0#
#102
1#
b01101101 '
b01101100 )
b000110011 *
b01101100 +
b000001011 ,
#103
0#
#104
1#
b000110100 *
b000001100 ,
#105
0#
#106
1#
b01101110 '
b01101101 )
b000110101 *
b01101101 +
b000001101 ,
#107
0#
#108
1#
b01101101 '
b01101100 )
b000110110 *
b01101100 +
b000001110 ,
#109
0#
#110
1#
b01101110 '
b000110111 *
b000001111 ,
#111
0#
#112
1#
b01101111 )
b000111000 *
b01101111 +
b000010000 ,
#113
0#
#114
1#
b01101100 '
b01110010 )
b000111001 *
b01110010 +
b000010001 ,
#115
0#
#116
1#
b01101111 '
b01101111 )
b000111010 *
b01101111 +
b000010010 ,
#117
0#
#118
1#
b01101110 '
b01110011 )
b000111011 *
b01110011 +
b000010011 ,
#119
0#
#120
1#
b01101111 '
b01110010 )
b000111100 *
b01110010 +
b000010100 ,
#121
0#
#122
1#
b01110001 )
b000111101 *
b01110001 +
b000010101 ,
#123
0#
#124
1#
b01101110 '
b01110000 )
b000111110 *
b01110000 +
b000010110 ,
#125
0#
#126
1#
b01101101 '
b000111111 *
b000010111 ,
#127
0#
#128
1#
b01101111 '
b01110011 )
b001000000 *
b01110011 +
b000011000 ,
#129
0#
#130
1#
b01110000 '
b01110001 )
b001000001 *
b01110001 +
b000011001 ,
#131
0#
#132
1#
b01101111 '
b01110011 )
b001000010 *
b01110011 +
b000011010 ,
#133
0#
#134
1#
b01110000 '
b01110010 )
b001000011 *
b01110010 +
b000011011 ,
#135
0#
#136
1#
b01101111 )
b001000100 *
b01101111 +
b000011100 ,
#137
0#
#138
1#
b01101100 )
b001000101 *
b01101100 +
b000011101 ,
#139
0#
#140
1#
b001000110 *
b000011110 ,
#141
0#
#142
1#
b01101110 '
b01101111 )
b001000111 *
b01101111 +
b000011111 ,
#143
0#
#144
1#
b01110010 '
b001001000 *
b000100000 ,
#145
0#
#146
1#
b001001001 *
b000100001 ,
#147
0#
#148
1#
b01110100 '
b01101010 )
b001001010 *
b01101010 +
b000100010 ,
#149
0#
#150
1#
b01110000 '
b01101011 )
b001001011 *
b01101011 +
b000100011 ,
#151
0#
#152
1#
b01101010 )
b001001100 *
b01101010 +
b000100100 ,
#153
0#
#154
1#
b01101110 '
b001001101 *
b000100101 ,
#155
0#
#156
1#
b01101111 '
b01101100 )
b001001110 *
b01101100 +
b000100110 ,
#157
0#
#158
1#
b01101110 '
b01101110 )
b001001111 *
b01101110 +
b000100111 ,
#159
0#
#160
1#
b01101111 '
b01110010 )
b001010000 *
b01110010 +
b000101000 ,
#161
0#
#162
1#
b01110011 '
b01101111 )
b001010001 *
b01101111 +
b000101001 ,
#163
0#
#164
1#
b01110010 '
b01110010 )
b001010010 *
b01110010 +
b000101010 ,
#165
0#
#166
1#
b01110011 '
b01110011 )
b001010011 *
b01110011 +
b000101011 ,
#167
0#
#168
1#
b01110000 '
b01110100 )
b001010100 *
b01110100 +
b000101100 ,
#169
0#
#170
1#
b01110000 )
b001010101 *
b01110000 +
b000101101 ,
#171
0#
#172
1#
b01110010 '
b01101111 )
b001010110 *
b01101111 +
b000101110 ,
#173
0#
#174
1#
b01101100 )
b001010111 *
b01101100 +
b000101111 ,
#175
0#
#176
1#
b01110101 '
b001011000 *
b000110000 ,
#177
0#
#178
1#
b01111000 '
b001011001 *
b000110001 ,
#179
0#
#180
1#
b01111001 '
b01101010 )
b001011010 *
b01101010 +
b000110010 ,
#181
0#
#182
1#
b01101110 )
b001011011 *
b01101110 +
b000110011 ,
#183
0#
#184
1#
b01110111 '
b01101101 )
b001011100 *
b01101101 +
b000110100 ,
#185
0#
#186
1#
b01110110 '
b001011101 *
b000110101 ,
#187
0#
#188
1#
b01110111 '
b01101110 )
b001011110 *
b01101110 +
b000110110 ,
#189
0#
#190
1#
b01111011 '
b01101101 )
b001011111 *
b01101101 +
b000110111 ,
#191
0#
#192
1#
b01111001 '
b01101110 )
b001100000 *
b01101110 +
b000111000 ,
#193
0#
#194
1#
b01110101 '
b001100001 *
b000111001 ,
#195
0#
#196
1#
b01110011 '
b01101100 )
b001100010 *
b01101100 +
b000111010 ,
#197
0#
#198
1#
b01110100 '
b01101111 )
b001100011 *
b01101111 +
b000111011 ,
#199
0#
#200
1#
b01110011 '
b01101110 )
b001100100 *
b01101110 +
b000111100 ,
#201
0#
#202
1#
b01110010 '
b01101111 )
b001100101 *
b01101111 +
b000111101 ,
#203
0#
#204
1#
b001100110 *
b000111110 ,
#205
0#
#206
1#
b01101110 )
b001100111 *
b01101110 +
b000111111 ,
#207
0#
#208
1#
b01101101 )
b001101000 *
b01101101 +
b001000000 ,
#209
0#
#210
1#
b01110001 '
b01101111 )
b001101001 *
b01101111 +
b001000001 ,
#211
0#
#212
1#
b01101100 '
b01110000 )
b001101010 *
b01110000 +
b001000010 ,
#213
0#
#214
1#
b01101011 '
b01101111 )
b001101011 *
b01101111 +
b001000011 ,
#215
0#
#216
1#
b01110000 )
b001101100 *
b01110000 +
b001000100 ,
#217
0#
#218
1#
b01101100 '
b001101101 *
b001000101 ,
#219
0#
#220
1#
b001101110 *
b001000110 ,
#221
0#
#222
1#
b001101111 *
b001000111 ,
#223
0#
#224
1#
b01101110 )
b001110000 *
b01101110 +
b001001000 ,
#225
0#
#226
1#
b01101010 '
b01110010 )
b001110001 *
b01110010 +
b001001001 ,
#227
0#
#228
1#
b01101101 '
b001110010 *
b001001010 ,
#229
0#
#230
1#
b01101001 '
b01110100 )
b001110011 *
b01110100 +
b001001011 ,
#231
0#
#232
1#
b01100111 '
b01110000 )
b001110100 *
b01110000 +
b001001100 ,
#233
0#
#234
1#
b01101000 '
b001110101 *
b001001101 ,
#235
0#
#236
1#
b01100111 '
b01101110 )
b001110110 *
b01101110 +
b001001110 ,
#237
0#
#238
1#
b01101001 '
b01101111 )
b001110111 *
b01101111 +
b001001111 ,
#239
0#
#240
1#
b01101110 )
b001111000 *
b01101110 +
b001010000 ,
#241
0#
#242
1#
b01101000 '
b01101111 )
b001111001 *
b01101111 +
b001010001 ,
#243
0#
#244
1#
b01110011 )
b001111010 *
b01110011 +
b001010010 ,
#245
0#
#246
1#
b01101010 '
b01110010 )
b001111011 *
b01110010 +
b001010011 ,
#247
0#
#248
1#
b01100111 '
b01110011 )
b001111100 *
b01110011 +
b001010100 ,
#249
0#
#250
1#
b01101100 '
b01110000 )
b001111101 *
b01110000 +
b001010101 ,
#251
0#
#252
1#
b01101111 '
b001111110 *
b001010110 ,
#253
0#
#254
1#
b01110000 '
b01110010 )
b001111111 *
b01110010 +
b001010111 ,
#255
0#
#256
1#
b01110010 '
b010000000 *
b001011000 ,
#257
0#
#258
1#
b01110101 )
b010000001 *
b01110101 +
b001011001 ,
#259
0#
#260
1#
b01111000 )
b010000010 *
b01111000 +
b001011010 ,
#261
0#
#262
1#
b01111001 )
b010000011 *
b01111001 +
b001011011 ,
#263
0#
#264
1#
b01110101 '
b010000100 *
b001011100 ,
#265
0#
#266
1#
b01110100 '
b01110111 )
b010000101 *
b01110111 +
b001011101 ,
#267
0#
#268
1#
b01110110 '
b01110110 )
b010000110 *
b01110110 +
b001011110 ,
#269
0#
#270
1#
b01110111 '
b01110111 )
b010000111 *
b01110111 +
b001011111 ,
#271
0#
#272
1#
b01110101 '
b01111011 )
b010001000 *
b01111011 +
b001100000 ,
#273
0#
#274
1#
b01110001 '
b01111001 )
b010001001 *
b01111001 +
b001100001 ,
#275
0#
#276
1#
b01110010 '
b01110101 )
b010001010 *
b01110101 +
b001100010 ,
#277
0#
#278
1#
b01101111 '
b01110011 )
b010001011 *
b01110011 +
b001100011 ,
#279
0#
#280
1#
b01101110 '
b01110100 )
b010001100 *
b01110100 +
b001100100 ,
#281
0#
#282
1#
b01101101 '
b01110011 )
b010001101 *
b01110011 +
b001100101 ,
#283
0#
#284
1#
b01101010 '
b01110010 )
b010001110 *
b01110010 +
b001100110 ,
#285
0#
#286
1#
b01101001 '
b010001111 *
b001100111 ,
#287
0#
#288
1#
b010010000 *
b001101000 ,
#289
0#
#290
1#
b01101100 '
b010010001 *
b001101001 ,
#291
0#
#292
1#
b01101000 '
b01110001 )
b010010010 *
b01110001 +
b001101010 ,
#293
0#
#294
1#
b01101010 '
b01101100 )
b010010011 *
b01101100 +
b001101011 ,
#295
0#
#296
1#
b01101100 '
b01101011 )
b010010100 *
b01101011 +
b001101100 ,
#297
0#
#298
1#
b01101101 '
b010010101 *
b001101101 ,
#299
0#
#300
1#
b01110000 '
b01101100 )
b010010110 *
b01101100 +
b001101110 ,
#301
0#
#302
1#
b01110001 '
b010010111 *
b001101111 ,
#303
0#
#304
1#
b01110011 '
b010011000 *
b001110000 ,
#305
0#
#306
1#
b01110100 '
b010011001 *
b001110001 ,
#307
0#
#308
1#
b01111010 '
b01101010 )
b010011010 *
b01101010 +
b001110010 ,
#309
0#
#310
1#
b01110101 '
b01101101 )
b010011011 *
b01101101 +
b001110011 ,
#311
0#
#312
1#
b01110010 '
b01101001 )
b010011100 *
b01101001 +
b001110100 ,
#313
0#
#314
1#
b01110100 '
b01100111 )
b010011101 *
b01100111 +
b001110101 ,
#315
0#
#316
1#
b01110010 '
b01101000 )
b010011110 *
b01101000 +
b001110110 ,
#317
0#
#318
1#
b01100111 )
b010011111 *
b01100111 +
b001110111 ,
#319
0#
#320
1#
b01110000 '
b01101001 )
b010100000 *
b01101001 +
b001111000 ,
#321
0#
#322
1#
b01101111 '
b010100001 *
b001111001 ,
#323
0#
#324
1#
b01101101 '
b01101000 )
b010100010 *
b01101000 +
b001111010 ,
#325
0#
#326
1#
b01101011 '
b010100011 *
b001111011 ,
#327
0#
#328
1#
b01100111 '
b01101010 )
b010100100 *
b01101010 +
b001111100 ,
#329
0#
#330
1#
b01101010 '
b01100111 )
b010100101 *
b01100111 +
b001111101 ,
#331
0#
#332
1#
b01100101 '
b01101100 )
b010100110 *
b01101100 +
b001111110 ,
#333
0#
#334
1#
b01100110 '
b01101111 )
b010100111 *
b01101111 +
b001111111 ,
#335
0#
#336
1#
b01100100 '
b01110000 )
b010101000 *
b01110000 +
b010000000 ,
#337
0#
#338
1#
b01100010 '
b01110010 )
b010101001 *
b01110010 +
b010000001 ,
#339
0#
#340
1#
b01100011 '
b010101010 *
b010000010 ,
#341
0#
#342
1#
b01100101 '
b010101011 *
b010000011 ,
#343
0#
#344
1#
b01100110 '
b010101100 *
b010000100 ,
#345
0#
#346
1#
b01100010 '
b01110101 )
b010101101 *
b01110101 +
b010000101 ,
#347
0#
#348
1#
b01100101 '
b01110100 )
b010101110 *
b01110100 +
b010000110 ,
#349
0#
#350
1#
b01100100 '
b01110110 )
b010101111 *
b01110110 +
b010000111 ,
#351
0#
#352
1#
b01101000 '
b01110111 )
b010110000 *
b01110111 +
b010001000 ,
#353
0#
#354
1#
b01101011 '
b01110101 )
b010110001 *
b01110101 +
b010001001 ,
#355
0#
#356
1#
b01110001 )
b010110010 *
b01110001 +
b010001010 ,
#357
0#
#358
1#
b01101000 '
b01110010 )
b010110011 *
b01110010 +
b010001011 ,
#359
0#
#360
1#
b01100101 '
b01101111 )
b010110100 *
b01101111 +
b010001100 ,
#361
0#
#362
1#
b01101110 )
b010110101 *
b01101110 +
b010001101 ,
#363
0#
#364
1#
b01100111 '
b01101101 )
b010110110 *
b01101101 +
b010001110 ,
#365
0#
#366
1#
b01101010 )
b010110111 *
b01101010 +
b010001111 ,
#367
0#
#368
1#
b01101011 '
b01101001 )
b010111000 *
b01101001 +
b010010000 ,
#369
0#
#370
1#
b01101001 '
b010111001 *
b010010001 ,
#371
0#
#372
1#
b01101011 '
b01101100 )
b010111010 *
b01101100 +
b010010010 ,
#373
0#
#374
1#
b01101000 )
b010111011 *
b01101000 +
b010010011 ,
#375
0#
#376
1#
b01101111 '
b01101010 )
b010111100 *
b01101010 +
b010010100 ,
#377
0#
#378
1#
b01101110 '
b01101100 )
b010111101 *
b01101100 +
b010010101 ,
#379
0#
#380
1#
b01110000 '
b01101101 )
b010111110 *
b01101101 +
b010010110 ,
#381
0#
#382
1#
b01110000 )
b010111111 *
b01110000 +
b010010111 ,
#383
0#
#384
1#
b01101101 '
b000101001 (
b01110001 )
b011000000 *
b01110001 +
#385
0#
#386
1#
b01110010 '
b011000001 *
b010011000 ,
#387
0#
#388
1#
b01101111 '
b000101010 (
b01110011 )
b011000010 *
b01110011 +
#389
0#
#390
1#
b000101011 (
b011000011 *
#391
0#
#392
1#
b01101101 '
b000101111 (
b011000100 *
b010010101 ,
#393
0#
#394
1#
b000110000 (
b01101101 )
b011000101 *
b01101101 +
#395
0#
#396
1#
b01101100 '
b000110010 (
b011000110 *
b010010100 ,
#397
0#
#398
1#
b01101011 '
b000110100 (
b01101100 )
b011000111 *
b01101100 +
b010010011 ,
#399
0#
#400
1#
b01101000 '
b01101010 )
b011001000 *
b01101010 +
b010010100 ,
#401
0#
#402
1#
b01100100 '
b01101100 )
b011001001 *
b01101100 +
b010010101 ,
#403
0#
#404
1#
b01100010 '
b01101101 )
b011001010 *
b01101101 +
b010010110 ,
#405
0#
#406
1#
b01100100 '
b01110000 )
b011001011 *
b01110000 +
b010010111 ,
#407
0#
#408
1#
b01100010 '
b01110001 )
b011001100 *
b01110001 +
b010011000 ,
#409
0#
#410
1#
b01100011 '
b01110011 )
b011001101 *
b01110011 +
b010011001 ,
#411
0#
#412
1#
b01100111 '
b01110100 )
b011001110 *
b01110100 +
b010011010 ,
#413
0#
#414
1#
b01101010 '
b01111010 )
b011001111 *
b01111010 +
b010011011 ,
#415
0#
#416
1#
b01101101 '
b01110101 )
b011010000 *
b01110101 +
b010011100 ,
#417
0#
#418
1#
b01110001 '
b01110010 )
b011010001 *
b01110010 +
b010011101 ,
#419
0#
#420
1#
b01110100 )
b011010010 *
b01110100 +
b010011110 ,
#421
0#
#422
1#
b01110100 '
b01110010 )
b011010011 *
b01110010 +
b010011111 ,
#423
0#
#424
1#
b01110110 '
b011010100 *
b010100000 ,
#425
0#
#426
1#
b01111001 '
b01110000 )
b011010101 *
b01110000 +
b010100001 ,
#427
0#
#428
1#
b01111000 '
b000110101 (
b01101111 )
b011010110 *
b01101111 +
#429
0#
#430
1#
b01110111 '
b000110111 (
b011010111 *
b010100000 ,
#431
0#
#432
1#
b000111001 (
b01110000 )
b011011000 *
b01110000 +
b010011111 ,
#433
0#
#434
1#
b000111011 (
b01110010 )
b011011001 *
b01110010 +
b010011110 ,
#435
0#
#436
1#
b01110010 '
b000111101 (
b011011010 *
b010011101 ,
#437
0#
#438
1#
b01110001 '
b01110100 )
b011011011 *
b01110100 +
b010011110 ,
#439
0#
#440
1#
b01110000 '
b01110010 )
b011011100 *
b01110010 +
b010011111 ,
#441
0#
#442
1#
b01101110 '
b011011101 *
b010100000 ,
#443
0#
#444
1#
b01101100 '
b01110000 )
b011011110 *
b01110000 +
b010100001 ,
#445
0#
#446
1#
b01101011 '
b01101111 )
b011011111 *
b01101111 +
b010100010 ,
#447
0#
#448
1#
b01101000 '
b01101101 )
b011100000 *
b01101101 +
b010100011 ,
#449
0#
#450
1#
b01100111 '
b01101011 )
b011100001 *
b01101011 +
b010100100 ,
#451
0#
#452
1#
b01100111 )
b011100010 *
b01100111 +
b010100101 ,
#453
0#
#454
1#
b01100110 '
b01101010 )
b011100011 *
b01101010 +
b010100110 ,
#455
0#
#456
1#
b01100101 '
b01100101 )
b011100100 *
b01100101 +
b010100111 ,
#457
0#
#458
1#
b01100110 )
b011100101 *
b01100110 +
b010101000 ,
#459
0#
#460
1#
b01101010 '
b01100100 )
b011100110 *
b01100100 +
b010101001 ,
#461
0#
#462
1#
b01101001 '
b01100010 )
b011100111 *
b01100010 +
b010101010 ,
#463
0#
#464
1#
b01100101 '
b01100011 )
b011101000 *
b01100011 +
b010101011 ,
#465
0#
#466
1#
b01100100 '
b01100101 )
b011101001 *
b01100101 +
b010101100 ,
#467
0#
#468
1#
b01100110 )
b011101010 *
b01100110 +
b010101101 ,
#469
0#
#470
1#
b01100010 )
b011101011 *
b01100010 +
b010101110 ,
#471
0#
#472
1#
b01100111 '
b01100101 )
b011101100 *
b01100101 +
b010101111 ,
#473
0#
#474
1#
b01100110 '
b01100100 )
b011101101 *
b01100100 +
b010110000 ,
#475
0#
#476
1#
b01100100 '
b01101000 )
b011101110 *
b01101000 +
b010110001 ,
#477
0#
#478
1#
b01100101 '
b01101011 )
b011101111 *
b01101011 +
b010110010 ,
#479
0#
#480
1#
b01100100 '
b011110000 *
b010110011 ,
#481
0#
#482
1#
b01101000 )
b011110001 *
b01101000 +
b010110100 ,
#483
0#
#484
1#
b01100001 '
b01100101 )
b011110010 *
b01100101 +
b010110101 ,
#485
0#
#486
1#
b01100010 '
b011110011 *
b010110110 ,
#487
0#
#488
1#
b01100100 '
b01100111 )
b011110100 *
b01100111 +
b010110111 ,
#489
0#
#490
1#
b01100111 '
b011110101 *
b010111000 ,
#491
0#
#492
1#
b01101011 )
b011110110 *
b01101011 +
b010111001 ,
#493
0#
#494
1#
b01101000 '
b01101001 )
b011110111 *
b01101001 +
b010111010 ,
#495
0#
#496
1#
b01100110 '
b01101011 )
b011111000 *
b01101011 +
b010111011 ,
#497
0#
#498
1#
b01101001 '
b011111001 *
b010111100 ,
#499
0#
#500
1#
b01101010 '
b01101111 )
b011111010 *
b01101111 +
b010111101 ,
#501
0#
#502
1#
b01100111 '
b01101110 )
b011111011 *
b01101110 +
b010111110 ,
#503
0#
#504
1#
b01110000 )
b011111100 *
b01110000 +
b010111111 ,
#505
0#
#506
1#
b01101011 '
b011111101 *
b011000000 ,
#507
0#
#508
1#
b01101110 '
b01101101 )
b011111110 *
b01101101 +
b011000001 ,
#509
0#
#510
1#
b01101101 '
b01110010 )
b011111111 *
b01110010 +
b011000010 ,
#511
0#
#512
1#
b01101010 '
b01101111 )
b100000000 *
b01101111 +
b011000011 ,
#513
0#
#514
1#
b01101001 '
b100000001 *
b011000100 ,
#515
0#
#516
1#
b01101010 '
b01101101 )
b100000010 *
b01101101 +
b011000101 ,
#517
0#
#518
1#
b01100111 '
b100000011 *
b011000110 ,
#519
0#
#520
1#
b01101100 )
b100000100 *
b01101100 +
b011000111 ,
#521
0#
#522
1#
b01101011 )
b100000101 *
b01101011 +
b011001000 ,
#523
0#
#524
1#
b01100110 '
b01101000 )
b100000110 *
b01101000 +
b011001001 ,
#525
0#
#526
1#
b01101000 '
b01100100 )
b100000111 *
b01100100 +
b011001010 ,
#527
0#
#528
1#
b01100100 '
b01100010 )
b100001000 *
b01100010 +
b011001011 ,
#529
0#
#530
1#
b01100111 '
b01100100 )
b100001001 *
b01100100 +
b011001100 ,
#531
0#
#532
1#
b01100100 '
b01100010 )
b100001010 *
b01100010 +
b011001101 ,
#533
0#
#534
1#
b01100110 '
b01100011 )
b100001011 *
b01100011 +
b011001110 ,
#535
0#
#536
1#
b01100111 )
b100001100 *
b01100111 +
b011001111 ,
#537
0#
#538
1#
b01101010 '
b01101010 )
b100001101 *
b01101010 +
b011010000 ,
#539
0#
#540
1#
b01101011 '
b01101101 )
b100001110 *
b01101101 +
b011010001 ,
#541
0#
#542
1#
b01101101 '
b01110001 )
b100001111 *
b01110001 +
b011010010 ,
#543
0#
#544
1#
b01101111 '
b100010000 *
b011010011 ,
#545
0#
#546
1#
b01110101 '
b01110100 )
b100010001 *
b01110100 +
b011010100 ,
#547
0#
#548
1#
b01110111 '
b01110110 )
b100010010 *
b01110110 +
b011010101 ,
#549
0#
#550
1#
b01110110 '
b01111001 )
b100010011 *
b01111001 +
b011010110 ,
#551
0#
#552
1#
b01111000 )
b100010100 *
b01111000 +
b011010111 ,
#553
0#
#554
1#
b01110101 '
b01110111 )
b100010101 *
b01110111 +
b011011000 ,
#555
0#
#556
1#
b01110110 '
b100010110 *
b011011001 ,
#557
0#
#558
1#
b01110001 '
b100010111 *
b011011010 ,
#559
0#
#560
1#
b01101111 '
b01110010 )
b100011000 *
b01110010 +
b011011011 ,
#561
0#
#562
1#
b01101100 '
b01110001 )
b100011001 *
b01110001 +
b011011100 ,
#563
0#
#564
1#
b01100110 '
b01110000 )
b100011010 *
b01110000 +
b011011101 ,
#565
0#
#566
1#
b01100111 '
b01101110 )
b100011011 *
b01101110 +
b011011110 ,
#567
0#
#568
1#
b01100101 '
b01101100 )
b100011100 *
b01101100 +
b011011111 ,
#569
0#
#570
1#
b01100010 '
b01101011 )
b100011101 *
b01101011 +
b011100000 ,
#571
0#
#572
1#
b01100001 '
b01101000 )
b100011110 *
b01101000 +
b011100001 ,
#573
0#
#574
1#
b01100000 '
b01100111 )
b100011111 *
b01100111 +
b011100010 ,
#575
0#
#576
1#
b01100010 '
b100100000 *
b011100011 ,
#577
0#
#578
1#
b01011111 '
b01100110 )
b100100001 *
b01100110 +
b011100100 ,
#579
0#
#580
1#
b01100101 )
b100100010 *
b01100101 +
b011100101 ,
#581
0#
#582
1#
b01100001 '
b100100011 *
b011100110 ,
#583
0#
#584
1#
b01100011 '
b01101010 )
b100100100 *
b01101010 +
b011100111 ,
#585
0#
#586
1#
b01011111 '
b01101001 )
b100100101 *
b01101001 +
b011101000 ,
#587
0#
#588
1#
b01100010 '
b01100101 )
b100100110 *
b01100101 +
b011101001 ,
#589
0#
#590
1#
b01100100 '
b01100100 )
b100100111 *
b01100100 +
b011101010 ,
#591
0#
#592
1#
b100101000 *
b011101011 ,
#593
0#
#594
1#
b01100110 '
b100101001 *
b011101100 ,
#595
0#
#596
1#
b01101001 '
b01100111 )
b100101010 *
b01100111 +
b011101101 ,
#597
0#
#598
1#
b01101010 '
b01100110 )
b100101011 *
b01100110 +
b011101110 ,
#599
0#
#600
1#
b01101000 '
b01100100 )
b100101100 *
b01100100 +
b011101111 ,
#601
0#
#602
1#
b01101001 '
b01100101 )
b100101101 *
b01100101 +
b011110000 ,
#603
0#
#604
1#
b01100100 )
b100101110 *
b01100100 +
b011110001 ,
#605
0#
#606
1#
b01100101 '
b100101111 *
b011110010 ,
#607
0#
#608
1#
b01100100 '
b01100001 )
b100110000 *
b01100001 +
b011110011 ,
#609
0#
#610
1#
b01100001 '
b01100010 )
b100110001 *
b01100010 +
b011110100 ,
#611
0#
#612
1#
b01100010 '
b01100100 )
b100110010 *
b01100100 +
b011110101 ,
#613
0#
#614
1#
b01100100 '
b01100111 )
b100110011 *
b01100111 +
b011110110 ,
#615
0#
#616
1#
b100110100 *
b011110111 ,
